{
  "$schema": "https://raw.githubusercontent.com/streetsidesoftware/cspell/main/packages/cspell-types/cspell.schema.json",
  "version": "0.2",
  "language": "en",
  "words": [
    "asyncio",
    "cuda",
    "cython",
    "dmypy",
    "etils",
    "getattr",
    "hynek",
    "ipynb",
    "ipython",
    "levelno",
    "libc",
    "liblaf",
    "mkdocs",
    "mypy",
    "ndarray",
    "numpy",
    "pipenv",
    "pixi",
    "prec",
    "pybuilder",
    "pycache",
    "pydantic",
    "pydocstyle",
    "pyenv",
    "pyflow",
    "pypa",
    "pypackages",
    "pypi",
    "pyplot",
    "pyproject",
    "pyrightconfig",
    "pytest",
    "pytype",
    "pyvista",
    "ruamel",
    "scrapy",
    "sdist",
    "serde",
    "stefanzweifel",
    "tomlkit",
    "trimesh",
    "ubelt",
    "venv"
  ],
  "ignorePaths": [
    "**/.cspell.*",
    "**/.git",
    "**/.vscode",
    "**/*-lock.*",
    "**/*.lock*"
  ],
  "allowCompoundWords": true
}
