{
  "Value": {
    "0": "0",
    "1": "1",
    "2": "2",
    "3": "3",
    "4": "4",
    "5": "5",
    "6": "6",
    "7": "7",
    "8": "8",
    "9": "9",
    "10": "10",
    "11": "11",
    "12": "12",
    "13": "13",
    "14": "14",
    "15": "15",
    "16": "16",
    "17": "17",
    "18": "18",
    "19": "19",
    "20": "20",
    "21": "21",
    "22": "22",
    "23": "23",
    "24": "24",
    "25": "25",
    "26": "26",
    "27": "27",
    "28": "28",
    "29": "29",
    "30": "30",
    "31": "31",
    "32": "32",
    "33": "33",
    "34": "34",
    "35": "35",
    "36": "36",
    "37": "37",
    "38": "38",
    "39": "39",
    "40": "40",
    "41": "41",
    "42": "42",
    "43": "43",
    "44": "44",
    "45": "45",
    "46": "46",
    "47": "47",
    "48": "48",
    "49": "49",
    "50": "50",
    "51": "51",
    "52": "52",
    "53": "53",
    "54": "54",
    "55": "55",
    "56": "56",
    "57": "57",
    "58": "58",
    "59": "59",
    "60": "60",
    "61": "61",
    "62": "62",
    "63": "63",
    "64": "64",
    "65": "65",
    "66": "66",
    "67": "67",
    "68": "68",
    "69": "69",
    "70": "70",
    "71": "71",
    "72": "72",
    "73": "73",
    "74": "74",
    "75": "75",
    "76": "76",
    "77": "77",
    "78": "78",
    "79": "79",
    "80": "80",
    "81": "81",
    "82": "82",
    "83": "83",
    "84": "84",
    "85": "85",
    "86": "86",
    "87": "87",
    "88": "88",
    "89": "89",
    "90": "90",
    "91": "91",
    "92": "92",
    "93": "93",
    "94": "94",
    "95": "95",
    "96": "96",
    "97": "97",
    "98": "98",
    "99": "99",
    "100": "100",
    "101": "101",
    "102": "102",
    "103": "103",
    "104": "104",
    "105": "105",
    "106": "106",
    "107": "—",
    "108": "—"
  },
  "_128A": {
    "0": "",
    "1": "!",
    "2": "\"",
    "3": "#",
    "4": "$",
    "5": "%",
    "6": "&",
    "7": "'",
    "8": "(",
    "9": ")",
    "10": "*",
    "11": "+",
    "12": ",",
    "13": "-",
    "14": ".",
    "15": "/",
    "16": "0",
    "17": "1",
    "18": "2",
    "19": "3",
    "20": "4",
    "21": "5",
    "22": "6",
    "23": "7",
    "24": "8",
    "25": "9",
    "26": ":",
    "27": ";",
    "28": "<",
    "29": "=",
    "30": ">",
    "31": "?",
    "32": "@",
    "33": "A",
    "34": "B",
    "35": "C",
    "36": "D",
    "37": "E",
    "38": "F",
    "39": "G",
    "40": "H",
    "41": "I",
    "42": "J",
    "43": "K",
    "44": "L",
    "45": "M",
    "46": "N",
    "47": "O",
    "48": "P",
    "49": "Q",
    "50": "R",
    "51": "S",
    "52": "T",
    "53": "U",
    "54": "V",
    "55": "W",
    "56": "X",
    "57": "Y",
    "58": "Z",
    "59": "[",
    "60": "\\",
    "61": "]",
    "62": "^",
    "63": "_",
    "64": "NUL",
    "65": "SOH",
    "66": "STX",
    "67": "ETX",
    "68": "EOT",
    "69": "ENQ",
    "70": "ACK",
    "71": "BEL",
    "72": "BS",
    "73": "HT",
    "74": "LF",
    "75": "VT",
    "76": "FF",
    "77": "CR",
    "78": "SO",
    "79": "SI",
    "80": "DLE",
    "81": "DC1",
    "82": "DC2",
    "83": "DC3",
    "84": "DC4",
    "85": "NAK",
    "86": "SYN",
    "87": "ETB",
    "88": "CAN",
    "89": "EM",
    "90": "SUB",
    "91": "ESC",
    "92": "FS",
    "93": "GS",
    "94": "RS",
    "95": "US",
    "96": "FNC 3",
    "97": "FNC 2",
    "98": "Shift B",
    "99": "Code C",
    "100": "Code B",
    "101": "FNC 4",
    "102": "FNC 1",
    "103": "Start Code A",
    "104": "Start Code B",
    "105": "Start Code C",
    "106": "Stop",
    "107": "Reverse Stop",
    "108": "Stop_pattern"
  },
  "_128B": {
    "0": "",
    "1": "!",
    "2": "\"",
    "3": "#",
    "4": "$",
    "5": "%",
    "6": "&",
    "7": "'",
    "8": "(",
    "9": ")",
    "10": "*",
    "11": "+",
    "12": ",",
    "13": "-",
    "14": ".",
    "15": "/",
    "16": "0",
    "17": "1",
    "18": "2",
    "19": "3",
    "20": "4",
    "21": "5",
    "22": "6",
    "23": "7",
    "24": "8",
    "25": "9",
    "26": ":",
    "27": ";",
    "28": "<",
    "29": "=",
    "30": ">",
    "31": "?",
    "32": "@",
    "33": "A",
    "34": "B",
    "35": "C",
    "36": "D",
    "37": "E",
    "38": "F",
    "39": "G",
    "40": "H",
    "41": "I",
    "42": "J",
    "43": "K",
    "44": "L",
    "45": "M",
    "46": "N",
    "47": "O",
    "48": "P",
    "49": "Q",
    "50": "R",
    "51": "S",
    "52": "T",
    "53": "U",
    "54": "V",
    "55": "W",
    "56": "X",
    "57": "Y",
    "58": "Z",
    "59": "[",
    "60": "\\",
    "61": "]",
    "62": "^",
    "63": "_",
    "64": "`",
    "65": "a",
    "66": "b",
    "67": "c",
    "68": "d",
    "69": "e",
    "70": "f",
    "71": "g",
    "72": "h",
    "73": "i",
    "74": "j",
    "75": "k",
    "76": "l",
    "77": "m",
    "78": "n",
    "79": "o",
    "80": "p",
    "81": "q",
    "82": "r",
    "83": "s",
    "84": "t",
    "85": "u",
    "86": "v",
    "87": "w",
    "88": "x",
    "89": "y",
    "90": "z",
    "91": "{",
    "92": "|",
    "93": "}",
    "94": "~",
    "95": "DEL",
    "96": "FNC 3",
    "97": "FNC 2",
    "98": "Shift A",
    "99": "Code C",
    "100": "FNC 4",
    "101": "Code A",
    "102": "FNC 1",
    "103": "Start Code A",
    "104": "Start Code B",
    "105": "Start Code C",
    "106": "Stop",
    "107": "Reverse Stop",
    "108": "Stop_pattern"
  },
  "_128C": {
    "0": "00",
    "1": "01",
    "2": "02",
    "3": "03",
    "4": "04",
    "5": "05",
    "6": "06",
    "7": "07",
    "8": "08",
    "9": "09",
    "10": "10",
    "11": "11",
    "12": "12",
    "13": "13",
    "14": "14",
    "15": "15",
    "16": "16",
    "17": "17",
    "18": "18",
    "19": "19",
    "20": "20",
    "21": "21",
    "22": "22",
    "23": "23",
    "24": "24",
    "25": "25",
    "26": "26",
    "27": "27",
    "28": "28",
    "29": "29",
    "30": "30",
    "31": "31",
    "32": "32",
    "33": "33",
    "34": "34",
    "35": "35",
    "36": "36",
    "37": "37",
    "38": "38",
    "39": "39",
    "40": "40",
    "41": "41",
    "42": "42",
    "43": "43",
    "44": "44",
    "45": "45",
    "46": "46",
    "47": "47",
    "48": "48",
    "49": "49",
    "50": "50",
    "51": "51",
    "52": "52",
    "53": "53",
    "54": "54",
    "55": "55",
    "56": "56",
    "57": "57",
    "58": "58",
    "59": "59",
    "60": "60",
    "61": "61",
    "62": "62",
    "63": "63",
    "64": "64",
    "65": "65",
    "66": "66",
    "67": "67",
    "68": "68",
    "69": "69",
    "70": "70",
    "71": "71",
    "72": "72",
    "73": "73",
    "74": "74",
    "75": "75",
    "76": "76",
    "77": "77",
    "78": "78",
    "79": "79",
    "80": "80",
    "81": "81",
    "82": "82",
    "83": "83",
    "84": "84",
    "85": "85",
    "86": "86",
    "87": "87",
    "88": "88",
    "89": "89",
    "90": "90",
    "91": "91",
    "92": "92",
    "93": "93",
    "94": "94",
    "95": "95",
    "96": "96",
    "97": "97",
    "98": "98",
    "99": "99",
    "100": "Code B",
    "101": "Code A",
    "102": "FNC 1",
    "103": "Start Code A",
    "104": "Start Code B",
    "105": "Start Code C",
    "106": "Stop",
    "107": "Reverse Stop",
    "108": "Stop_pattern"
  },
  "Font_position_code": {
    "0": "32 or 194 or 207 / 212 / 252",
    "1": "33",
    "2": "34",
    "3": "35",
    "4": "36",
    "5": "37",
    "6": "38",
    "7": "39",
    "8": "40",
    "9": "41",
    "10": "42",
    "11": "43",
    "12": "44",
    "13": "45",
    "14": "46",
    "15": "47",
    "16": "48",
    "17": "49",
    "18": "50",
    "19": "51",
    "20": "52",
    "21": "53",
    "22": "54",
    "23": "55",
    "24": "56",
    "25": "57",
    "26": "58",
    "27": "59",
    "28": "60",
    "29": "61",
    "30": "62",
    "31": "63",
    "32": "64",
    "33": "65",
    "34": "66",
    "35": "67",
    "36": "68",
    "37": "69",
    "38": "70",
    "39": "71",
    "40": "72",
    "41": "73",
    "42": "74",
    "43": "75",
    "44": "76",
    "45": "77",
    "46": "78",
    "47": "79",
    "48": "80",
    "49": "81",
    "50": "82",
    "51": "83",
    "52": "84",
    "53": "85",
    "54": "86",
    "55": "87",
    "56": "88",
    "57": "89",
    "58": "90",
    "59": "91",
    "60": "92",
    "61": "93",
    "62": "94",
    "63": "95",
    "64": "96",
    "65": "97",
    "66": "98",
    "67": "99",
    "68": "100",
    "69": "101",
    "70": "102",
    "71": "103",
    "72": "104",
    "73": "105",
    "74": "106",
    "75": "107",
    "76": "108",
    "77": "109",
    "78": "110",
    "79": "111",
    "80": "112",
    "81": "113",
    "82": "114",
    "83": "115",
    "84": "116",
    "85": "117",
    "86": "118",
    "87": "119",
    "88": "120",
    "89": "121",
    "90": "122",
    "91": "123",
    "92": "124",
    "93": "125",
    "94": "126",
    "95": "195 / 200 / 240",
    "96": "196 / 201 / 241",
    "97": "197 / 202 / 242",
    "98": "198 / 203 / 243",
    "99": "199 / 204 / 244",
    "100": "200 / 205 / 245",
    "101": "201 / 206 / 246",
    "102": "202 / 207 / 247",
    "103": "203 / 208 / 248",
    "104": "204 / 209 / 249",
    "105": "205 / 210 / 250",
    "106": "—",
    "107": "—",
    "108": "206 / 211 / 251"
  },
  "Font_position_latin_1": {
    "0": "␣ or Â or Ï / Ô / ü",
    "1": "!",
    "2": "\"",
    "3": "#",
    "4": "$",
    "5": "%",
    "6": "&",
    "7": "'",
    "8": "(",
    "9": ")",
    "10": "*",
    "11": "+",
    "12": ",",
    "13": "-",
    "14": ".",
    "15": "/",
    "16": "0",
    "17": "1",
    "18": "2",
    "19": "3",
    "20": "4",
    "21": "5",
    "22": "6",
    "23": "7",
    "24": "8",
    "25": "9",
    "26": ":",
    "27": ";",
    "28": "<",
    "29": "=",
    "30": ">",
    "31": "?",
    "32": "@",
    "33": "A",
    "34": "B",
    "35": "C",
    "36": "D",
    "37": "E",
    "38": "F",
    "39": "G",
    "40": "H",
    "41": "I",
    "42": "J",
    "43": "K",
    "44": "L",
    "45": "M",
    "46": "N",
    "47": "O",
    "48": "P",
    "49": "Q",
    "50": "R",
    "51": "S",
    "52": "T",
    "53": "U",
    "54": "V",
    "55": "W",
    "56": "X",
    "57": "Y",
    "58": "Z",
    "59": "[",
    "60": "\\",
    "61": "]",
    "62": "^",
    "63": "_",
    "64": "`",
    "65": "a",
    "66": "b",
    "67": "c",
    "68": "d",
    "69": "e",
    "70": "f",
    "71": "g",
    "72": "h",
    "73": "i",
    "74": "j",
    "75": "k",
    "76": "l",
    "77": "m",
    "78": "n",
    "79": "o",
    "80": "p",
    "81": "q",
    "82": "r",
    "83": "s",
    "84": "t",
    "85": "u",
    "86": "v",
    "87": "w",
    "88": "x",
    "89": "y",
    "90": "z",
    "91": "{",
    "92": "|",
    "93": "}",
    "94": "~",
    "95": "Ã / È / ð",
    "96": "Ä / É / ñ",
    "97": "Å / Ê / ò",
    "98": "Æ / Ë / ó",
    "99": "Ç / Ì / ô",
    "100": "È / Í / õ",
    "101": "É / Î / ö",
    "102": "Ê / Ï / ÷",
    "103": "Ë / Ð / ø",
    "104": "Ì / Ñ / ù",
    "105": "Í / Ò / ú",
    "106": "—",
    "107": "—",
    "108": "Î / Ó / û"
  },
  "bar_pattern": {
    "0": "11011001100",
    "1": "11001101100",
    "2": "11001100110",
    "3": "10010011000",
    "4": "10010001100",
    "5": "10001001100",
    "6": "10011001000",
    "7": "10011000100",
    "8": "10001100100",
    "9": "11001001000",
    "10": "11001000100",
    "11": "11000100100",
    "12": "10110011100",
    "13": "10011011100",
    "14": "10011001110",
    "15": "10111001100",
    "16": "10011101100",
    "17": "10011100110",
    "18": "11001110010",
    "19": "11001011100",
    "20": "11001001110",
    "21": "11011100100",
    "22": "11001110100",
    "23": "11101101110",
    "24": "11101001100",
    "25": "11100101100",
    "26": "11100100110",
    "27": "11101100100",
    "28": "11100110100",
    "29": "11100110010",
    "30": "11011011000",
    "31": "11011000110",
    "32": "11000110110",
    "33": "10100011000",
    "34": "10001011000",
    "35": "10001000110",
    "36": "10110001000",
    "37": "10001101000",
    "38": "10001100010",
    "39": "11010001000",
    "40": "11000101000",
    "41": "11000100010",
    "42": "10110111000",
    "43": "10110001110",
    "44": "10001101110",
    "45": "10111011000",
    "46": "10111000110",
    "47": "10001110110",
    "48": "11101110110",
    "49": "11010001110",
    "50": "11000101110",
    "51": "11011101000",
    "52": "11011100010",
    "53": "11011101110",
    "54": "11101011000",
    "55": "11101000110",
    "56": "11100010110",
    "57": "11101101000",
    "58": "11101100010",
    "59": "11100011010",
    "60": "11101111010",
    "61": "11001000010",
    "62": "11110001010",
    "63": "10100110000",
    "64": "10100001100",
    "65": "10010110000",
    "66": "10010000110",
    "67": "10000101100",
    "68": "10000100110",
    "69": "10110010000",
    "70": "10110000100",
    "71": "10011010000",
    "72": "10011000010",
    "73": "10000110100",
    "74": "10000110010",
    "75": "11000010010",
    "76": "11001010000",
    "77": "11110111010",
    "78": "11000010100",
    "79": "10001111010",
    "80": "10100111100",
    "81": "10010111100",
    "82": "10010011110",
    "83": "10111100100",
    "84": "10011110100",
    "85": "10011110010",
    "86": "11110100100",
    "87": "11110010100",
    "88": "11110010010",
    "89": "11011011110",
    "90": "11011110110",
    "91": "11110110110",
    "92": "10101111000",
    "93": "10100011110",
    "94": "10001011110",
    "95": "10111101000",
    "96": "10111100010",
    "97": "11110101000",
    "98": "11110100010",
    "99": "10111011110",
    "100": "10111101110",
    "101": "11101011110",
    "102": "11110101110",
    "103": "11010000100",
    "104": "11010010000",
    "105": "11010011100",
    "106": "11000111010",
    "107": "11010111000",
    "108": "1100011101011"
  },
  "bar_widths": {
    "0": "212222",
    "1": "222122",
    "2": "222221",
    "3": "121223",
    "4": "121322",
    "5": "131222",
    "6": "122213",
    "7": "122312",
    "8": "132212",
    "9": "221213",
    "10": "221312",
    "11": "231212",
    "12": "112232",
    "13": "122132",
    "14": "122231",
    "15": "113222",
    "16": "123122",
    "17": "123221",
    "18": "223211",
    "19": "221132",
    "20": "221231",
    "21": "213212",
    "22": "223112",
    "23": "312131",
    "24": "311222",
    "25": "321122",
    "26": "321221",
    "27": "312212",
    "28": "322112",
    "29": "322211",
    "30": "212123",
    "31": "212321",
    "32": "232121",
    "33": "111323",
    "34": "131123",
    "35": "131321",
    "36": "112313",
    "37": "132113",
    "38": "132311",
    "39": "211313",
    "40": "231113",
    "41": "231311",
    "42": "112133",
    "43": "112331",
    "44": "132131",
    "45": "113123",
    "46": "113321",
    "47": "133121",
    "48": "313121",
    "49": "211331",
    "50": "231131",
    "51": "213113",
    "52": "213311",
    "53": "213131",
    "54": "311123",
    "55": "311321",
    "56": "331121",
    "57": "312113",
    "58": "312311",
    "59": "332111",
    "60": "314111",
    "61": "221411",
    "62": "431111",
    "63": "111224",
    "64": "111422",
    "65": "121124",
    "66": "121421",
    "67": "141122",
    "68": "141221",
    "69": "112214",
    "70": "112412",
    "71": "122114",
    "72": "122411",
    "73": "142112",
    "74": "142211",
    "75": "241211",
    "76": "221114",
    "77": "413111",
    "78": "241112",
    "79": "134111",
    "80": "111242",
    "81": "121142",
    "82": "121241",
    "83": "114212",
    "84": "124112",
    "85": "124211",
    "86": "411212",
    "87": "421112",
    "88": "421211",
    "89": "212141",
    "90": "214121",
    "91": "412121",
    "92": "111143",
    "93": "111341",
    "94": "131141",
    "95": "114113",
    "96": "114311",
    "97": "411113",
    "98": "411311",
    "99": "113141",
    "100": "114131",
    "101": "311141",
    "102": "411131",
    "103": "211412",
    "104": "211214",
    "105": "211232",
    "106": "233111",
    "107": "211133",
    "108": "2331112"
  }
}